aiomcp/__init__.py
aiomcp/mcp_client.py
aiomcp/mcp_schema_resolver.py
aiomcp/mcp_serialization.py
aiomcp/mcp_server.py
aiomcp/mcp_transport_resolver.py
aiomcp/py.typed
aiomcp/contracts/mcp_message.py
aiomcp/contracts/mcp_schema.py
aiomcp/contracts/mcp_tool.py
aiomcp/transports/base.py
aiomcp/transports/direct.py
aiomcp/transports/http.py
aiomcp/transports/memory.py
aiomcp-0.0.3.dist-info/licenses/LICENSE
aiomcp-0.0.3.dist-info/METADATA
aiomcp-0.0.3.dist-info/WHEEL
aiomcp-0.0.3.dist-info/top_level.txt
aiomcp-0.0.3.dist-info/RECORD
