Metadata-Version: 2.4
Name: aiomcp
Version: 0.0.3
Summary: A Simple Python MCP Solution
Requires-Python: >=3.10
License-File: LICENSE
Requires-Dist: pydantic
Requires-Dist: aiohttp
Provides-Extra: test
Requires-Dist: pytest; extra == "test"
Requires-Dist: pytest-asyncio; extra == "test"
Dynamic: license-file
